spqr_0_0_1/__init__.py
spqr_0_0_1/spqr.py
spqr_0_0_1/spqr_defines.py
spqr_0_0_1/spqr_events.py
spqr_0_0_1/spqr_extras.py
spqr_0_0_1/spqr_gui.py
spqr_0_0_1/spqr_menu.py
spqr_0_0_1/spqr_widgets.py
spqr_0_0_1/spqr_window.py
SPQRGames-0.0.1.dist-info/LICENSE
SPQRGames-0.0.1.dist-info/METADATA
SPQRGames-0.0.1.dist-info/WHEEL
SPQRGames-0.0.1.dist-info/top_level.txt
SPQRGames-0.0.1.dist-info/RECORD
