Metadata-Version: 2.1
Name: SPQRGames
Version: 0.0.1
Summary: SPQR Games
Home-page: https://github.com/CHUA-X/SPQRGames
Author: CHUA某人
Author-email: CHUA某人 <chua-x@outlook.com>
Project-URL: Homepage, https://github.com/CHUA-X/SPQRGames
Project-URL: Bug Tracker, https://github.com/CHUA-X/SPQRGames/issues
Classifier: Development Status :: 2 - Pre-Alpha
Classifier: Programming Language :: Python :: 3
Classifier: Programming Language :: Python :: 3 :: Only
Classifier: License :: OSI Approved :: BSD License
Classifier: Natural Language :: Chinese (Simplified)
Classifier: Natural Language :: English
Classifier: Operating System :: Unix
Classifier: Operating System :: POSIX :: Linux
Classifier: Operating System :: MacOS :: MacOS X
Classifier: Operating System :: Microsoft :: Windows
Requires-Python: >=3.6
License-File: LICENSE
